Metadata-Version: 2.1
Name: uRAD-firmware
Version: 1.0.0
Summary: uRAD firmware library and script that reads the raw dara from the uRAD system
Home-page: https://github.com/Kananelo688
Author: Kananelo Chabeli
Author-email: kchabeli688@gmail.com
Classifier: Programming Language :: Python :: 3
Classifier: License :: OSI Approved :: MIT License
Classifier: Operating System :: OS Independent
Requires-Python: >=3.6
License-File: LICENSE
Requires-Dist: pyserial
